llmcxt/__init__.py
llmcxt/cli.py
llmcxt/core/__init__.py
llmcxt/core/config_manager.py
llmcxt/core/context_manager.py
llmcxt/core/file_manager.py
llmcxt/core/ignore_manager.py
llmcxt/utils/__init__.py
llmcxt/utils/helpers.py
llmcxt-0.1.3.dist-info/METADATA
llmcxt-0.1.3.dist-info/WHEEL
llmcxt-0.1.3.dist-info/entry_points.txt
llmcxt-0.1.3.dist-info/top_level.txt
llmcxt-0.1.3.dist-info/RECORD
