Metadata-Version: 2.1
Name: llmcxt
Version: 0.1.3
Summary: A tool to manage and generate context for Large Language Models from project files
Home-page: https://github.com/cabeywic/llmcxt.git
Author: Charaka Abeywickrama
Author-email: Charaka Abeywickrama <charaka.abeywickrama@gmail.com>
Project-URL: Homepage, https://github.com/cabeywic/llmcxt.git
Keywords: llm,context,cli
Classifier: Programming Language :: Python :: 3
Classifier: License :: OSI Approved :: MIT License
Classifier: Operating System :: OS Independent
Requires-Python: >=3.6
Requires-Dist: Click
Requires-Dist: pyperclip
